py_slvs/__init__.py
py_slvs/_slvs.so
py_slvs/slvs.py
py_slvs.libs/libgcc_s-2298274a.so.1
py_slvs.libs/libstdc++-08d5c7eb.so.6.0.33
py_slvs-1.0.6.dist-info/LICENSE
py_slvs-1.0.6.dist-info/METADATA
py_slvs-1.0.6.dist-info/WHEEL
py_slvs-1.0.6.dist-info/top_level.txt
py_slvs-1.0.6.dist-info/RECORD
