Metadata-Version: 2.1
Name: py-slvs
Version: 1.0.6
Summary: Python binding of SOLVESPACE geometry constraint solver
Home-page: https://github.com/realthunder/slvs_py
Author: Zheng, Lei
Author-email: realthunder.dev@gmail.com
License: Gnu General Public License 3.0
License-File: LICENSE
